flask_cavage.py
setup.cfg
setup.py
Flask_Cavage.egg-info/PKG-INFO
Flask_Cavage.egg-info/SOURCES.txt
Flask_Cavage.egg-info/dependency_links.txt
Flask_Cavage.egg-info/not-zip-safe
Flask_Cavage.egg-info/requires.txt
Flask_Cavage.egg-info/top_level.txt