Metadata-Version: 1.1
Name: Flask-Cavage
Version: 0.2
Summary: Verify cavage signed http requests
Home-page: https://github.com/labeneator/flask_cavage
Author: Laban Mwangi
Author-email: lmwangi@gmail.com
License: GPLv3
Platform: any
Classifier: Development Status :: 4 - Beta
Classifier: Environment :: Web Environment
Classifier: Intended Audience :: Developers
Classifier: License :: OSI Approved :: BSD License
Classifier: Operating System :: OS Independent
Classifier: Programming Language :: Python
Classifier: Topic :: Internet :: WWW/HTTP :: Dynamic Content
Classifier: Topic :: Software Development :: Libraries :: Python Modules
